conduct/__init__.py
conduct/exceptions.py
conduct/models.py
conduct-0.0.0.dist-info/LICENSE
conduct-0.0.0.dist-info/METADATA
conduct-0.0.0.dist-info/WHEEL
conduct-0.0.0.dist-info/top_level.txt
conduct-0.0.0.dist-info/RECORD
