Metadata-Version: 2.1
Name: conduct
Version: 0.0.0
Summary: Lightning nodes conductor, with a code.
Home-page: https://github.com/lnbits/conduct
Author: eillarra
Author-email: eneko@illarra.com
License: MIT
Keywords: bitcoin lightning-network
Platform: UNKNOWN
Classifier: Development Status :: 1 - Planning
Classifier: Intended Audience :: Developers
Classifier: License :: OSI Approved :: MIT License
Classifier: Operating System :: OS Independent
Classifier: Programming Language :: Python
Classifier: Programming Language :: Python :: 3
Classifier: Programming Language :: Python :: 3.6
Classifier: Programming Language :: Python :: 3.7
Classifier: Programming Language :: Python :: 3.8
Classifier: Topic :: Utilities
Requires-Dist: httpx
Provides-Extra: full
Requires-Dist: lnd-grpc ; extra == 'full'
Requires-Dist: pylightning ; extra == 'full'
